{
  "name": "Multi-Language Dev Environment",
  "build": {
    "dockerfile": "Dockerfile"
  },
  "customizations": {
    "vscode": {
      "extensions": [
        "dbaeumer.vscode-eslint",
        "esbenp.prettier-vscode",
        "GitHub.copilot",
        "golang.go",
        "ms-dotnettools.csdevkit",
        "ms-dotnettools.csharp",
        "ms-python.python",
        "ms-python.vscode-pylance",
        "ms-vscode.cmake-tools",
        "ms-vscode.cpptools",
        "ms-vsliveshare.vsliveshare",
        "rust-lang.rust-analyzer",
        "vscjava.vscode-java-pack"
      ],
      "settings": {
        "terminal.integrated.defaultProfile.linux": "bash"
      }
    }
  },
  "forwardPorts": [],
  "postCreateCommand": "echo 'Dev container ready!'",
  "remoteUser": "vscode"
}
